[
  {
    "id": "starter_bundle",
    "name": "新手禮包",
    "description": "適合新手的道具組合包，包含基礎製作材料。",
    "type": "bundle",  
    "items": [     
      {
        "item_id": "bone",
        "quantity": 10
      },
      {
        "item_id": "slime_core", 
        "quantity": 5
      },
      {
        "item_id": "moss_branches",
        "quantity": 3
      }
    ],
    "cost": {
      "world_boss_token": 5
    },
    "reset_type": "weekly",
    "limit_per_account": 10,
    "limit_per_reset": 2,
    "sort": 50,
    "available": true,
    "special": 1,
    "category": "materials"
  },
  {
    "id": "premium_bundle",
    "name": "高級製作禮包",
    "description": "高級製作材料禮包，包含稀有材料和混沌氣息。",
    "type": "bundle",
    "items": [
      {
        "item_id": "chaos_breath",
        "quantity": 2
      },
      {
        "item_id": "swamp_core",
        "quantity": 3
      },
      {
        "item_id": "sky_ragments", 
        "quantity": 2
      },
      {
        "item_id": "magic_fragment",
        "quantity": 1
      }
    ],
    "cost": {
      "world_boss_token": 30
    },
    "reset_type": "monthly",
    "limit_per_account": 5,
    "limit_per_reset": 1,
    "sort": 10,
    "available": true,
    "special": 2,
    "category": "materials"
  },
  
  {
    "id": "shop_chaos_breath",
    "name": "混沌氣息",
    "description": "狩獵怪物有很低的機率掉落的混沌氣息。製作高級卡片的重要材料。",
    "item_id": "chaos_breath",
    "quantity": 1,
    "cost": {
      "world_boss_token": 10
    },
    "type": "trade",
    "reset_type": "weekly",
    "limit_per_account": 20,
    "limit_per_reset": 3,
    "sort": 100,
    "available": true,
    "special": 2,
    "category": "materials"
  }
]
